book_strands/__init__.py
book_strands/agent.py
book_strands/cli.py
book_strands/constants.py
book_strands/utils.py
book_strands/tools/__init__.py
book_strands/tools/download_ebook.py
book_strands/tools/filesystem.py
book_strands/tools/lookup_books.py
book_strands/tools/read_ebook_metadata.py
book_strands/tools/write_ebook_metadata.py
book_strands-0.7.6.dist-info/METADATA
book_strands-0.7.6.dist-info/WHEEL
book_strands-0.7.6.dist-info/entry_points.txt
book_strands-0.7.6.dist-info/RECORD
