Metadata-Version: 2.4
Name: book-strands
Version: 0.7.6
Summary: A powerful CLI tool for managing e-book metadata and organizing your digital library.
Author-email: Justin Dray <justin@dray.be>
Requires-Python: >=3.12
Requires-Dist: beautifulsoup4>=4.13.4
Requires-Dist: click>=8.0.0
Requires-Dist: ebooklib>=0.19
Requires-Dist: strands-agents-tools>=0.2.13
Requires-Dist: strands-agents[ollama,otel]>=1.14.0
